lib_pcg/__init__.py
lib_pcg/consts.py
lib_pcg/pcg128.py
lib_pcg/pcg32.py
lib_pcg/pcg64.py
lib_pcg/py.typed
lib_pcg_algopy-1.0.0.dist-info/METADATA
lib_pcg_algopy-1.0.0.dist-info/WHEEL
lib_pcg_algopy-1.0.0.dist-info/RECORD
