Metadata-Version: 2.4
Name: lib-pcg-algopy
Version: 1.0.0
Summary: PCG library implemented using Algorand Python
License: MIT
Author: Giorgio Ciotti
Author-email: gciotti.dev@gmail.com
Requires-Python: >=3.12,<4.0
Classifier: License :: OSI Approved :: MIT License
Classifier: Programming Language :: Python :: 3
Classifier: Programming Language :: Python :: 3.12
Classifier: Programming Language :: Python :: 3.13
Classifier: Programming Language :: Python :: 3.14
Requires-Dist: algorand-python (>=3,<4)
Project-URL: Repository, https://github.com/CiottiGiorgio/lib-pcg-avm
